{
    "sample_id": "S01_PBMC_unstimulated_S1",
    "product_id": "single-cell-pna",
    "report_type": "collapse-umi",
    "region_id": "umi-1",
    "input_reads": 45667614,
    "input_molecules": 29976170,
    "input_unique_umis": 5053476,
    "output_unique_umis": 4654147,
    "corrected_unique_umis": 399329,
    "corrected_reads": 445542,
    "processed_files": [
        {
            "path": "S01_PBMC_unstimulated_S1.demux.m1.part_003.parquet",
            "file_size": 638049148,
            "molecule_count": 29976170
        }
    ],
    "markers": [
        {
            "marker": "CD18",
            "region_id": "umi-1",
            "input_reads": 3230714,
            "input_molecules": 2123218,
            "input_unique_umis": 368810,
            "corrected_reads": 34433,
            "corrected_unique_umis": 30987,
            "output_unique_umis": 337823,
            "output_reads": 3230714,
            "corrected_reads_fraction": 0.010658015534646521,
            "corrected_unique_umis_fraction": 0.08401887150565332
        },
        {
            "marker": "CD8",
            "region_id": "umi-1",
            "input_reads": 4991802,
            "input_molecules": 3276715,
            "input_unique_umis": 518052,
            "corrected_reads": 48123,
            "corrected_unique_umis": 43279,
            "output_unique_umis": 474773,
            "output_reads": 4991802,
            "corrected_reads_fraction": 0.00964040641035041,
            "corrected_unique_umis_fraction": 0.08354180661400785
        },
        {
            "marker": "CD20",
            "region_id": "umi-1",
            "input_reads": 433804,
            "input_molecules": 283637,
            "input_unique_umis": 43649,
            "corrected_reads": 4198,
            "corrected_unique_umis": 3860,
            "output_unique_umis": 39789,
            "output_reads": 433804,
            "corrected_reads_fraction": 0.009677181399894883,
            "corrected_unique_umis_fraction": 0.08843272469014181
        },
        {
            "marker": "CD22",
            "region_id": "umi-1",
            "input_reads": 695332,
            "input_molecules": 456010,
            "input_unique_umis": 72905,
            "corrected_reads": 7054,
            "corrected_unique_umis": 6494,
            "output_unique_umis": 66411,
            "output_reads": 695332,
            "corrected_reads_fraction": 0.010144794141503627,
            "corrected_unique_umis_fraction": 0.08907482340031547
        },
        {
            "marker": "CD328",
            "region_id": "umi-1",
            "input_reads": 1723424,
            "input_molecules": 1130400,
            "input_unique_umis": 193408,
            "corrected_reads": 17813,
            "corrected_unique_umis": 16100,
            "output_unique_umis": 177308,
            "output_reads": 1723424,
            "corrected_reads_fraction": 0.01033581985628609,
            "corrected_unique_umis_fraction": 0.08324371277299801
        },
        {
            "marker": "mIgG2a",
            "region_id": "umi-1",
            "input_reads": 171467,
            "input_molecules": 111856,
            "input_unique_umis": 22408,
            "corrected_reads": 1792,
            "corrected_unique_umis": 1639,
            "output_unique_umis": 20769,
            "output_reads": 171467,
            "corrected_reads_fraction": 0.010450990569613978,
            "corrected_unique_umis_fraction": 0.07314352017136737
        },
        {
            "marker": "CD152",
            "region_id": "umi-1",
            "input_reads": 43812,
            "input_molecules": 28702,
            "input_unique_umis": 5681,
            "corrected_reads": 472,
            "corrected_unique_umis": 411,
            "output_unique_umis": 5270,
            "output_reads": 43812,
            "corrected_reads_fraction": 0.010773304117593353,
            "corrected_unique_umis_fraction": 0.07234641788417533
        },
        {
            "marker": "CD159a",
            "region_id": "umi-1",
            "input_reads": 291568,
            "input_molecules": 190066,
            "input_unique_umis": 32045,
            "corrected_reads": 2819,
            "corrected_unique_umis": 2582,
            "output_unique_umis": 29463,
            "output_reads": 291568,
            "corrected_reads_fraction": 0.00966841354332437,
            "corrected_unique_umis_fraction": 0.08057419254173818
        },
        {
            "marker": "CD163",
            "region_id": "umi-1",
            "input_reads": 50123,
            "input_molecules": 32823,
            "input_unique_umis": 6335,
            "corrected_reads": 506,
            "corrected_unique_umis": 458,
            "output_unique_umis": 5877,
            "output_reads": 50123,
            "corrected_reads_fraction": 0.010095165891905912,
            "corrected_unique_umis_fraction": 0.07229676400947119
        },
        {
            "marker": "CD45RO",
            "region_id": "umi-1",
            "input_reads": 1482353,
            "input_molecules": 973703,
            "input_unique_umis": 162885,
            "corrected_reads": 14160,
            "corrected_unique_umis": 12806,
            "output_unique_umis": 150079,
            "output_reads": 1482353,
            "corrected_reads_fraction": 0.00955238057331823,
            "corrected_unique_umis_fraction": 0.07861988519507628
        },
        {
            "marker": "CD79a",
            "region_id": "umi-1",
            "input_reads": 348028,
            "input_molecules": 228016,
            "input_unique_umis": 37221,
            "corrected_reads": 4584,
            "corrected_unique_umis": 4006,
            "output_unique_umis": 33215,
            "output_reads": 348028,
            "corrected_reads_fraction": 0.013171354028986174,
            "corrected_unique_umis_fraction": 0.10762741463152521
        },
        {
            "marker": "CD80",
            "region_id": "umi-1",
            "input_reads": 236504,
            "input_molecules": 154908,
            "input_unique_umis": 29560,
            "corrected_reads": 2597,
            "corrected_unique_umis": 2370,
            "output_unique_umis": 27190,
            "output_reads": 236504,
            "corrected_reads_fraction": 0.01098078679430369,
            "corrected_unique_umis_fraction": 0.08017591339648174
        },
        {
            "marker": "CD199",
            "region_id": "umi-1",
            "input_reads": 386351,
            "input_molecules": 251710,
            "input_unique_umis": 42413,
            "corrected_reads": 4074,
            "corrected_unique_umis": 3718,
            "output_unique_umis": 38695,
            "output_reads": 386351,
            "corrected_reads_fraction": 0.01054481546572935,
            "corrected_unique_umis_fraction": 0.08766180180605003
        },
        {
            "marker": "CD95",
            "region_id": "umi-1",
            "input_reads": 923801,
            "input_molecules": 606260,
            "input_unique_umis": 106434,
            "corrected_reads": 10110,
            "corrected_unique_umis": 9175,
            "output_unique_umis": 97259,
            "output_reads": 923801,
            "corrected_reads_fraction": 0.01094391541035353,
            "corrected_unique_umis_fraction": 0.0862036567262341
        },
        {
            "marker": "CD6",
            "region_id": "umi-1",
            "input_reads": 6802837,
            "input_molecules": 4487891,
            "input_unique_umis": 759308,
            "corrected_reads": 64116,
            "corrected_unique_umis": 56621,
            "output_unique_umis": 702687,
            "output_reads": 6802837,
            "corrected_reads_fraction": 0.009424891409275278,
            "corrected_unique_umis_fraction": 0.07456921302027636
        },
        {
            "marker": "CD319",
            "region_id": "umi-1",
            "input_reads": 245986,
            "input_molecules": 160647,
            "input_unique_umis": 32338,
            "corrected_reads": 2779,
            "corrected_unique_umis": 2521,
            "output_unique_umis": 29817,
            "output_reads": 245986,
            "corrected_reads_fraction": 0.011297390908425683,
            "corrected_unique_umis_fraction": 0.07795782052074958
        },
        {
            "marker": "CD134",
            "region_id": "umi-1",
            "input_reads": 67946,
            "input_molecules": 44227,
            "input_unique_umis": 7659,
            "corrected_reads": 713,
            "corrected_unique_umis": 650,
            "output_unique_umis": 7009,
            "output_reads": 67946,
            "corrected_reads_fraction": 0.010493627292261502,
            "corrected_unique_umis_fraction": 0.084867476171824
        },
        {
            "marker": "CD161",
            "region_id": "umi-1",
            "input_reads": 461853,
            "input_molecules": 301855,
            "input_unique_umis": 55127,
            "corrected_reads": 4854,
            "corrected_unique_umis": 4416,
            "output_unique_umis": 50711,
            "output_reads": 461853,
            "corrected_reads_fraction": 0.010509837545712598,
            "corrected_unique_umis_fraction": 0.08010593719955739
        },
        {
            "marker": "CD62P",
            "region_id": "umi-1",
            "input_reads": 1034655,
            "input_molecules": 680414,
            "input_unique_umis": 99830,
            "corrected_reads": 10283,
            "corrected_unique_umis": 9185,
            "output_unique_umis": 90645,
            "output_reads": 1034655,
            "corrected_reads_fraction": 0.009938578560003093,
            "corrected_unique_umis_fraction": 0.0920064108985275
        },
        {
            "marker": "CD84",
            "region_id": "umi-1",
            "input_reads": 1064299,
            "input_molecules": 697418,
            "input_unique_umis": 111793,
            "corrected_reads": 11124,
            "corrected_unique_umis": 10063,
            "output_unique_umis": 101730,
            "output_reads": 1064299,
            "corrected_reads_fraction": 0.010451950062905255,
            "corrected_unique_umis_fraction": 0.09001458051935274
        },
        {
            "marker": "CD9",
            "region_id": "umi-1",
            "input_reads": 2497284,
            "input_molecules": 1631375,
            "input_unique_umis": 282792,
            "corrected_reads": 25236,
            "corrected_unique_umis": 22929,
            "output_unique_umis": 259863,
            "output_reads": 2497284,
            "corrected_reads_fraction": 0.010105378483184132,
            "corrected_unique_umis_fraction": 0.08108079436476279
        },
        {
            "marker": "CD43",
            "region_id": "umi-1",
            "input_reads": 17554415,
            "input_molecules": 11515707,
            "input_unique_umis": 1957468,
            "corrected_reads": 163832,
            "corrected_unique_umis": 146312,
            "output_unique_umis": 1811156,
            "output_reads": 17554415,
            "corrected_reads_fraction": 0.009332808868879994,
            "corrected_unique_umis_fraction": 0.0747455386243862
        },
        {
            "marker": "CD47",
            "region_id": "umi-1",
            "input_reads": 929256,
            "input_molecules": 608612,
            "input_unique_umis": 105355,
            "corrected_reads": 9870,
            "corrected_unique_umis": 8747,
            "output_unique_umis": 96608,
            "output_reads": 929256,
            "corrected_reads_fraction": 0.010621400346083318,
            "corrected_unique_umis_fraction": 0.08302406150633572
        }
    ]
}