{
    "sample_id": "S01_PBMC_unstimulated_S1",
    "product_id": "single-cell-pna",
    "report_type": "collapse-umi",
    "region_id": "umi-1",
    "input_reads": 58834059,
    "input_molecules": 38668365,
    "input_unique_umis": 6527561,
    "output_unique_umis": 6059241,
    "corrected_unique_umis": 468320,
    "corrected_reads": 518195,
    "processed_files": [
        {
            "path": "S01_PBMC_unstimulated_S1.demux.m1.part_004.parquet",
            "file_size": 838099547,
            "molecule_count": 38668365
        }
    ],
    "markers": [
        {
            "marker": "TCRab",
            "region_id": "umi-1",
            "input_reads": 3400419,
            "input_molecules": 2221517,
            "input_unique_umis": 367161,
            "corrected_reads": 34513,
            "corrected_unique_umis": 31258,
            "output_unique_umis": 335903,
            "output_reads": 3400419,
            "corrected_reads_fraction": 0.010149631560110681,
            "corrected_unique_umis_fraction": 0.08513431437434804
        },
        {
            "marker": "CD45",
            "region_id": "umi-1",
            "input_reads": 16828838,
            "input_molecules": 11139190,
            "input_unique_umis": 1854384,
            "corrected_reads": 134191,
            "corrected_unique_umis": 122309,
            "output_unique_umis": 1732075,
            "output_reads": 16828838,
            "corrected_reads_fraction": 0.007973871992825649,
            "corrected_unique_umis_fraction": 0.06595667348294636
        },
        {
            "marker": "CD19",
            "region_id": "umi-1",
            "input_reads": 393866,
            "input_molecules": 256268,
            "input_unique_umis": 45247,
            "corrected_reads": 4403,
            "corrected_unique_umis": 4043,
            "output_unique_umis": 41204,
            "output_reads": 393866,
            "corrected_reads_fraction": 0.011178928874287194,
            "corrected_unique_umis_fraction": 0.08935399031980021
        },
        {
            "marker": "CD44",
            "region_id": "umi-1",
            "input_reads": 16140800,
            "input_molecules": 10600309,
            "input_unique_umis": 1969129,
            "corrected_reads": 136874,
            "corrected_unique_umis": 123126,
            "output_unique_umis": 1846003,
            "output_reads": 16140800,
            "corrected_reads_fraction": 0.008480000991276765,
            "corrected_unique_umis_fraction": 0.06252815331042304
        },
        {
            "marker": "CD29",
            "region_id": "umi-1",
            "input_reads": 3603659,
            "input_molecules": 2381141,
            "input_unique_umis": 403944,
            "corrected_reads": 31731,
            "corrected_unique_umis": 28722,
            "output_unique_umis": 375222,
            "output_reads": 3603659,
            "corrected_reads_fraction": 0.008805217141799488,
            "corrected_unique_umis_fraction": 0.07110391539421305
        },
        {
            "marker": "CD35",
            "region_id": "umi-1",
            "input_reads": 2030876,
            "input_molecules": 1330127,
            "input_unique_umis": 206110,
            "corrected_reads": 19829,
            "corrected_unique_umis": 18131,
            "output_unique_umis": 187979,
            "output_reads": 2030876,
            "corrected_reads_fraction": 0.009763766965585294,
            "corrected_unique_umis_fraction": 0.08796759012177963
        },
        {
            "marker": "CD41",
            "region_id": "umi-1",
            "input_reads": 4491365,
            "input_molecules": 2944453,
            "input_unique_umis": 476519,
            "corrected_reads": 39272,
            "corrected_unique_umis": 35152,
            "output_unique_umis": 441367,
            "output_reads": 4491365,
            "corrected_reads_fraction": 0.00874388966383271,
            "corrected_unique_umis_fraction": 0.07376830724483179
        },
        {
            "marker": "CD56",
            "region_id": "umi-1",
            "input_reads": 112617,
            "input_molecules": 73196,
            "input_unique_umis": 13326,
            "corrected_reads": 1163,
            "corrected_unique_umis": 1071,
            "output_unique_umis": 12255,
            "output_reads": 112617,
            "corrected_reads_fraction": 0.010327037658612821,
            "corrected_unique_umis_fraction": 0.08036920306168392
        },
        {
            "marker": "CD81",
            "region_id": "umi-1",
            "input_reads": 1072455,
            "input_molecules": 695543,
            "input_unique_umis": 127070,
            "corrected_reads": 12496,
            "corrected_unique_umis": 11102,
            "output_unique_umis": 115968,
            "output_reads": 1072455,
            "corrected_reads_fraction": 0.011651770936775902,
            "corrected_unique_umis_fraction": 0.08736916660108601
        },
        {
            "marker": "CD93",
            "region_id": "umi-1",
            "input_reads": 703988,
            "input_molecules": 459960,
            "input_unique_umis": 72135,
            "corrected_reads": 7216,
            "corrected_unique_umis": 6380,
            "output_unique_umis": 65755,
            "output_reads": 703988,
            "corrected_reads_fraction": 0.010250174718887254,
            "corrected_unique_umis_fraction": 0.08844527621820199
        },
        {
            "marker": "CD231",
            "region_id": "umi-1",
            "input_reads": 86475,
            "input_molecules": 56366,
            "input_unique_umis": 10908,
            "corrected_reads": 838,
            "corrected_unique_umis": 760,
            "output_unique_umis": 10148,
            "output_reads": 86475,
            "corrected_reads_fraction": 0.009690662041052327,
            "corrected_unique_umis_fraction": 0.06967363403006967
        },
        {
            "marker": "TCRVg9",
            "region_id": "umi-1",
            "input_reads": 71925,
            "input_molecules": 46814,
            "input_unique_umis": 8049,
            "corrected_reads": 714,
            "corrected_unique_umis": 664,
            "output_unique_umis": 7385,
            "output_reads": 71925,
            "corrected_reads_fraction": 0.009927007299270074,
            "corrected_unique_umis_fraction": 0.08249471984097403
        },
        {
            "marker": "TIGIT",
            "region_id": "umi-1",
            "input_reads": 280064,
            "input_molecules": 182832,
            "input_unique_umis": 30730,
            "corrected_reads": 2938,
            "corrected_unique_umis": 2732,
            "output_unique_umis": 27998,
            "output_reads": 280064,
            "corrected_reads_fraction": 0.010490459323583182,
            "corrected_unique_umis_fraction": 0.08890335177351123
        },
        {
            "marker": "CD191",
            "region_id": "umi-1",
            "input_reads": 657649,
            "input_molecules": 428597,
            "input_unique_umis": 74036,
            "corrected_reads": 7025,
            "corrected_unique_umis": 6270,
            "output_unique_umis": 67766,
            "output_reads": 657649,
            "corrected_reads_fraction": 0.010681989936881223,
            "corrected_unique_umis_fraction": 0.08468852990437084
        },
        {
            "marker": "CD268",
            "region_id": "umi-1",
            "input_reads": 448834,
            "input_molecules": 293996,
            "input_unique_umis": 51324,
            "corrected_reads": 4445,
            "corrected_unique_umis": 4115,
            "output_unique_umis": 47209,
            "output_reads": 448834,
            "corrected_reads_fraction": 0.009903438687799944,
            "corrected_unique_umis_fraction": 0.08017691528329826
        },
        {
            "marker": "CD40",
            "region_id": "umi-1",
            "input_reads": 832551,
            "input_molecules": 543841,
            "input_unique_umis": 94195,
            "corrected_reads": 8720,
            "corrected_unique_umis": 7976,
            "output_unique_umis": 86219,
            "output_reads": 832551,
            "corrected_reads_fraction": 0.010473832834264807,
            "corrected_unique_umis_fraction": 0.0846754073995435
        },
        {
            "marker": "CD11a",
            "region_id": "umi-1",
            "input_reads": 4396437,
            "input_molecules": 2866443,
            "input_unique_umis": 376435,
            "corrected_reads": 39980,
            "corrected_unique_umis": 35865,
            "output_unique_umis": 340570,
            "output_reads": 4396437,
            "corrected_reads_fraction": 0.009093727488873377,
            "corrected_unique_umis_fraction": 0.0952754127538619
        },
        {
            "marker": "CD7",
            "region_id": "umi-1",
            "input_reads": 261475,
            "input_molecules": 170566,
            "input_unique_umis": 29880,
            "corrected_reads": 2820,
            "corrected_unique_umis": 2574,
            "output_unique_umis": 27306,
            "output_reads": 261475,
            "corrected_reads_fraction": 0.010784969882397934,
            "corrected_unique_umis_fraction": 0.086144578313253
        },
        {
            "marker": "CD53",
            "region_id": "umi-1",
            "input_reads": 1071215,
            "input_molecules": 702548,
            "input_unique_umis": 115417,
            "corrected_reads": 9741,
            "corrected_unique_umis": 8816,
            "output_unique_umis": 106601,
            "output_reads": 1071215,
            "corrected_reads_fraction": 0.009093412620248969,
            "corrected_unique_umis_fraction": 0.07638389492015908
        },
        {
            "marker": "CD34",
            "region_id": "umi-1",
            "input_reads": 37039,
            "input_molecules": 24333,
            "input_unique_umis": 4827,
            "corrected_reads": 381,
            "corrected_unique_umis": 362,
            "output_unique_umis": 4465,
            "output_reads": 37039,
            "corrected_reads_fraction": 0.010286454817894652,
            "corrected_unique_umis_fraction": 0.07499482079966853
        },
        {
            "marker": "CD369",
            "region_id": "umi-1",
            "input_reads": 300974,
            "input_molecules": 196586,
            "input_unique_umis": 31831,
            "corrected_reads": 2961,
            "corrected_unique_umis": 2708,
            "output_unique_umis": 29123,
            "output_reads": 300974,
            "corrected_reads_fraction": 0.009838059101450624,
            "corrected_unique_umis_fraction": 0.08507429863969086
        },
        {
            "marker": "CD54",
            "region_id": "umi-1",
            "input_reads": 1610538,
            "input_molecules": 1053739,
            "input_unique_umis": 164904,
            "corrected_reads": 15944,
            "corrected_unique_umis": 14184,
            "output_unique_umis": 150720,
            "output_reads": 1610538,
            "corrected_reads_fraction": 0.009899797458985756,
            "corrected_unique_umis_fraction": 0.08601368068694513
        }
    ]
}